MyriaPythonWorker/__init__.py
MyriaPythonWorker/serializers.py
MyriaPythonWorker/worker.py
MyriaPythonWorker-0.31.dist-info/DESCRIPTION.rst
MyriaPythonWorker-0.31.dist-info/METADATA
MyriaPythonWorker-0.31.dist-info/RECORD
MyriaPythonWorker-0.31.dist-info/WHEEL
MyriaPythonWorker-0.31.dist-info/metadata.json
MyriaPythonWorker-0.31.dist-info/top_level.txt
