Metadata-Version: 2.0
Name: MyriaPythonWorker
Version: 0.31
Summary: Myria Python worker.
Home-page: https://github.com/uwescience/myria
Author: Parmita Mehta
Author-email: UNKNOWN
License: UNKNOWN
Platform: UNKNOWN
Classifier: Development Status :: 3 - Alpha
Requires-Dist: pip (>=1.5.6)
